{
	"version": "1",
	"id": "66acd000-77fe-1000-9115-d802545107f4",
	"title": "Stuntman: Ignition",
	"image": "http://download.xbox.com/content/images/66acd000-77fe-1000-9115-d802545107f4/1033/boxartlg.jpg",
	"backgroundImage": "http://download.xbox.com/content/images/66acd000-77fe-1000-9115-d802545107f4/1033/background.jpg",
	"downloadTypeClass": "Game",
	"downloadTypeText": "Game",
	"platform": "Xbox",
	"description": "(Online Interactions Not Rated by the ESRB) This game supports English, French, Italian, German, and Spanish. Download the manual for this game by locating the game on http://marketplace.xbox.com and selecting “See Game Manual\". Plunge into the adrenaline-fueled role of a Hollywood stunt driver in Stuntman®: Ignition™, and master the most breathtaking, death-defying vehicle-based stunts ever filmed.  As the newest stuntman in Hollywood, you must rise to stardom by combining reckless maneuvering with perfect execution to unlock big-budget blockbusters and lucrative commercial deals. Create movie magic in six uniquely themed films on 36 different stunt runs with over 25 vehicles, or take the action online to challenge rival stuntmen in the ultimate backlot showdown. There are no refunds for this item. For more information, see www.xbox.com/live/accounts.",
	"genres": [
		{
			"label": "Action & Adventure"
		},
		{
			"label": "Racing & Flying"
		}
	],
	"publisher": "THQ",
	"studio": "Paradigm Entertainment",
	"originalReleaseDate": "/Date(1279152000000)/",
	"contentRating": {
		"label": "T (Teen)",
		"image": "http://epix.xbox.com/consoleassets/vm_ems/DetailsPages/RatingSystemID/0/default/Values/30.png",
		"age": 13,
		"purchaseAgeGate": false,
		"videoAgeGate": false,
		"descriptors": [
			{
				"label": "Violence",
				"image": null
			}
		],
		"disclaimers": [

		]
	},
	"trailers": [

	],
	"gameManual": null,
	"screenshots": [
		"http://download.xbox.com/content/images/66acd000-77fe-1000-9115-d802545107f4/1033/screenlg1.jpg",
		"http://download.xbox.com/content/images/66acd000-77fe-1000-9115-d802545107f4/1033/screenlg2.jpg",
		"http://download.xbox.com/content/images/66acd000-77fe-1000-9115-d802545107f4/1033/screenlg3.jpg",
		"http://download.xbox.com/content/images/66acd000-77fe-1000-9115-d802545107f4/1033/screenlg4.jpg",
		"http://download.xbox.com/content/images/66acd000-77fe-1000-9115-d802545107f4/1033/screenlg5.jpg",
		"http://download.xbox.com/content/images/66acd000-77fe-1000-9115-d802545107f4/1033/screenlg6.jpg",
		"http://download.xbox.com/content/images/66acd000-77fe-1000-9115-d802545107f4/1033/screenlg7.jpg",
		"http://download.xbox.com/content/images/66acd000-77fe-1000-9115-d802545107f4/1033/screenlg8.jpg",
		"http://download.xbox.com/content/images/66acd000-77fe-1000-9115-d802545107f4/1033/screenlg9.jpg",
		"http://download.xbox.com/content/images/66acd000-77fe-1000-9115-d802545107f4/1033/screenlg10.jpg",
		"http://download.xbox.com/content/images/66acd000-77fe-1000-9115-d802545107f4/1033/screenlg11.jpg",
		"http://download.xbox.com/content/images/66acd000-77fe-1000-9115-d802545107f4/1041/screenlg12.jpg"
	],
	"detailsUrl": "/en-US/Product/Stuntman-Ignition/66acd000-77fe-1000-9115-d802545107f4",
	"userRating": {
		"allowed": true,
		"current": {
			"Aggregate": 3.75,
			"Count": 7305
		}
	},
	"price": {
		"goldPrice": "$14.99",
		"silverPrice": "$14.99"
	},
	"prices": [
		{
			"method": "currency",
			"amount": 14.99,
			"display": "$14.99",
			"tax": "plus tax",
			"user": "silver"
		}
	],
	"childDownloadTypes": [
		"Game",
		"GameDemo",
		"GameVideo",
		"GameAddon",
		"GamerPic",
		"Theme"
	],
	"childDownloadsUrl": "/en-US/X8/Game/66acd000-77fe-1000-9115-d802545107f4/Children",
	"childDownloads": [
		{
			"id": "00000000-0000-4003-803f-0001545107f4",
			"title": "Stuntman : Ignition Theme 1",
			"description": "Customize your XBox 360 with these Hollywood-style images from Stuntman: Ignition. There are no refunds for this item. For more information, see www.xbox.com/live/accounts.",
			"userRating": {
				"allowed": true,
				"current": {
					"Aggregate": 3.5,
					"Count": 25
				}
			},
			"originalReleaseDate": "/Date(1196413200000)/",
			"contentRating": null,
			"childDownloadTypes": null,
			"genres": [
				{
					"label": "Action & Adventure"
				},
				{
					"label": "Racing & Flying"
				}
			],
			"image": "http://download.xbox.com/content/images/66acd000-77fe-1000-9115-d802545107f4/1033/boxartlg.jpg",
			"url": "/en-US/X8/Game/00000000-0000-4003-803f-0001545107f4",
			"downloadTypeClass": "Theme",
			"downloadTypeText": "Theme",
			"platform": "Xbox",
			"price": {
				"goldPrice": "$0.63",
				"silverPrice": "$0.63"
			},
			"prices": [
				{
					"method": "currency",
					"amount": 0.63,
					"display": "$0.63",
					"tax": "plus tax",
					"user": "silver"
				}
			]
		},
		{
			"id": "00000000-0000-4003-803f-0002545107f4",
			"title": "Stuntman : Ignition Theme 2",
			"description": "Customize your XBox 360 with these Hollywood-style images from Stuntman: Ignition. There are no refunds for this item. For more information, see www.xbox.com/live/accounts.",
			"userRating": {
				"allowed": true,
				"current": {
					"Aggregate": 3.75,
					"Count": 28
				}
			},
			"originalReleaseDate": "/Date(1196413200000)/",
			"contentRating": null,
			"childDownloadTypes": null,
			"genres": [
				{
					"label": "Action & Adventure"
				},
				{
					"label": "Racing & Flying"
				}
			],
			"image": "http://download.xbox.com/content/images/66acd000-77fe-1000-9115-d802545107f4/1033/boxartlg.jpg",
			"url": "/en-US/X8/Game/00000000-0000-4003-803f-0002545107f4",
			"downloadTypeClass": "Theme",
			"downloadTypeText": "Theme",
			"platform": "Xbox",
			"price": {
				"goldPrice": "$0.63",
				"silverPrice": "$0.63"
			},
			"prices": [
				{
					"method": "currency",
					"amount": 0.63,
					"display": "$0.63",
					"tax": "plus tax",
					"user": "silver"
				}
			]
		},
		{
			"id": "00000000-0000-4002-802f-0002545107f4",
			"title": "Stuntman Character Picture Pack 2",
			"description": "Download this 6 picture pack featuring heroes and villains from the movies of Stuntman: Ignition. There are no refunds for this item. For more information, see www.xbox.com/live/accounts.",
			"userRating": {
				"allowed": true,
				"current": {
					"Aggregate": 3.75,
					"Count": 36
				}
			},
			"originalReleaseDate": "/Date(1196413200000)/",
			"contentRating": null,
			"childDownloadTypes": null,
			"genres": [
				{
					"label": "Action & Adventure"
				},
				{
					"label": "Racing & Flying"
				}
			],
			"image": "http://download.xbox.com/content/images/66acd000-77fe-1000-9115-d802545107f4/1033/boxartlg.jpg",
			"url": "/en-US/X8/Game/00000000-0000-4002-802f-0002545107f4",
			"downloadTypeClass": "GamerPic",
			"downloadTypeText": "GamerPic",
			"platform": "Xbox",
			"price": {
				"goldPrice": "$1.49",
				"silverPrice": "$1.49"
			},
			"prices": [
				{
					"method": "currency",
					"amount": 1.49,
					"display": "$1.49",
					"tax": "plus tax",
					"user": "silver"
				}
			]
		},
		{
			"id": "00000000-0000-400c-80cf-0001545107f4",
			"title": "Stuntman Director's Cut Pack",
			"description": "Take on new challenges by downloading this Director's Cut package.  There are no refunds for this item. For more information, see www.xbox.com/live/accounts.",
			"userRating": {
				"allowed": true,
				"current": {
					"Aggregate": 3.75,
					"Count": 46
				}
			},
			"originalReleaseDate": "/Date(1196413200000)/",
			"contentRating": {
				"label": "T (Teen)",
				"image": "http://epix.xbox.com/consoleassets/vm_ems/DetailsPages/RatingSystemID/0/default/Values/30.png",
				"age": 13,
				"purchaseAgeGate": false,
				"videoAgeGate": false,
				"descriptors": [
					{
						"label": "Violence",
						"image": null
					}
				],
				"disclaimers": [

				]
			},
			"childDownloadTypes": null,
			"genres": [
				{
					"label": "Action & Adventure"
				},
				{
					"label": "Racing & Flying"
				}
			],
			"image": "http://download.xbox.com/content/images/66acd000-77fe-1000-9115-d802545107f4/1033/boxartlg.jpg",
			"url": "/en-US/X8/Game/00000000-0000-400c-80cf-0001545107f4",
			"downloadTypeClass": "GameAddon",
			"downloadTypeText": "Add-on",
			"platform": "Xbox",
			"price": {
				"goldPrice": "$9.99",
				"silverPrice": "$9.99"
			},
			"prices": [
				{
					"method": "currency",
					"amount": 9.99,
					"display": "$9.99",
					"tax": "plus tax",
					"user": "silver"
				}
			]
		},
		{
			"id": "66acd000-77fe-1000-9115-d802545107f4",
			"title": "Stuntman: Ignition",
			"description": "(Online Interactions Not Rated by the ESRB) This game supports English, French, Italian, German, and Spanish. Download the manual for this game by locating the game on http://marketplace.xbox.com and selecting “See Game Manual\". Plunge into the adrenaline-fueled role of a Hollywood stunt driver in Stuntman®: Ignition™, and master the most breathtaking, death-defying vehicle-based stunts ever filmed.  As the newest stuntman in Hollywood, you must rise to stardom by combining reckless maneuvering with perfect execution to unlock big-budget blockbusters and lucrative commercial deals. Create movie magic in six uniquely themed films on 36 different stunt runs with over 25 vehicles, or take the action online to challenge rival stuntmen in the ultimate backlot showdown. There are no refunds for this item. For more information, see www.xbox.com/live/accounts.",
			"userRating": {
				"allowed": true,
				"current": {
					"Aggregate": 3.75,
					"Count": 7305
				}
			},
			"originalReleaseDate": "/Date(1279616400000)/",
			"contentRating": {
				"label": "T (Teen)",
				"image": "http://epix.xbox.com/consoleassets/vm_ems/DetailsPages/RatingSystemID/0/default/Values/30.png",
				"age": 13,
				"purchaseAgeGate": false,
				"videoAgeGate": false,
				"descriptors": [
					{
						"label": "Violence",
						"image": null
					}
				],
				"disclaimers": [

				]
			},
			"childDownloadTypes": [
				"Game",
				"GameDemo",
				"GameVideo",
				"GameAddon",
				"GamerPic",
				"Theme"
			],
			"genres": [
				{
					"label": "Action & Adventure"
				},
				{
					"label": "Racing & Flying"
				}
			],
			"image": "http://download.xbox.com/content/images/66acd000-77fe-1000-9115-d802545107f4/1033/boxartlg.jpg",
			"url": "/en-US/X8/Game/66acd000-77fe-1000-9115-d802545107f4",
			"downloadTypeClass": "Game",
			"downloadTypeText": "Game",
			"platform": "Xbox",
			"price": {
				"goldPrice": "$14.99",
				"silverPrice": "$14.99"
			},
			"prices": [
				{
					"method": "currency",
					"amount": 14.99,
					"display": "$14.99",
					"tax": "plus tax",
					"user": "silver"
				}
			]
		},
		{
			"id": "00000000-0000-400d-80df-000154518813",
			"title": "Stuntman: Ignition Demo",
			"description": "Plunge into the adrenaline-fueled role of a Hollywood stunt driver to master the most breathtaking, death-defying vehicle-based stunts ever filmed in this brand new demo!",
			"userRating": {
				"allowed": true,
				"current": {
					"Aggregate": 3.5,
					"Count": 626
				}
			},
			"originalReleaseDate": "/Date(1184058000000)/",
			"contentRating": {
				"label": "T (Teen)",
				"image": "http://epix.xbox.com/consoleassets/vm_ems/DetailsPages/RatingSystemID/0/default/Values/30.png",
				"age": 13,
				"purchaseAgeGate": false,
				"videoAgeGate": false,
				"descriptors": [
					{
						"label": "Violence",
						"image": null
					}
				],
				"disclaimers": [

				]
			},
			"childDownloadTypes": null,
			"genres": [
				{
					"label": "Action & Adventure"
				},
				{
					"label": "Racing & Flying"
				}
			],
			"image": "http://download.xbox.com/content/images/00000000-0000-400d-80df-000154518813/1033/boxartlg.jpg",
			"url": "/en-US/X8/Game/00000000-0000-400d-80df-000154518813",
			"downloadTypeClass": "GameDemo",
			"downloadTypeText": "Demo",
			"platform": "Xbox",
			"price": {
				"goldPrice": "Free",
				"silverPrice": "Free"
			},
			"prices": [
				{
					"method": "currency",
					"amount": 0,
					"display": "Free",
					"tax": "plus tax",
					"user": "silver"
				}
			]
		},
		{
			"id": "00000000-0000-400b-80bf-0002545107f4",
			"title": "Stuntman: Ignition Trailer (HD)",
			"description": "Stuntman: Ignition plunges you into the adrenaline-fueled role of a Hollywood stunt driver to master the most breathtaking, death-defying vehicle-based stunts ever filmed.",
			"userRating": {
				"allowed": true,
				"current": {
					"Aggregate": 4.25,
					"Count": 37
				}
			},
			"originalReleaseDate": "/Date(1185958800000)/",
			"contentRating": {
				"label": "T (Teen)",
				"image": "http://epix.xbox.com/consoleassets/vm_ems/DetailsPages/RatingSystemID/0/default/Values/30.png",
				"age": 13,
				"purchaseAgeGate": false,
				"videoAgeGate": false,
				"descriptors": [
					{
						"label": "Violence",
						"image": null
					}
				],
				"disclaimers": [

				]
			},
			"childDownloadTypes": null,
			"genres": [
				{
					"label": "Action & Adventure"
				},
				{
					"label": "Racing & Flying"
				}
			],
			"image": "http://download.xbox.com/content/images/66acd000-77fe-1000-9115-d802545107f4/1033/boxartlg.jpg",
			"url": "/en-US/X8/Game/00000000-0000-400b-80bf-0002545107f4",
			"downloadTypeClass": "GameVideo",
			"downloadTypeText": "Video",
			"platform": "Xbox",
			"price": {
				"goldPrice": "Free",
				"silverPrice": "Free"
			},
			"prices": [
				{
					"method": "currency",
					"amount": 0,
					"display": "Free",
					"tax": "plus tax",
					"user": "silver"
				}
			]
		},
		{
			"id": "00000000-0000-400b-80bf-0001545107f4",
			"title": "Stuntman: Ignition Trailer (SD)",
			"description": "Stuntman: Ignition plunges you into the adrenaline-fueled role of a Hollywood stunt driver to master the most breathtaking, death-defying vehicle-based stunts ever filmed.",
			"userRating": {
				"allowed": true,
				"current": {
					"Aggregate": 4,
					"Count": 35
				}
			},
			"originalReleaseDate": "/Date(1185958800000)/",
			"contentRating": {
				"label": "T (Teen)",
				"image": "http://epix.xbox.com/consoleassets/vm_ems/DetailsPages/RatingSystemID/0/default/Values/30.png",
				"age": 13,
				"purchaseAgeGate": false,
				"videoAgeGate": false,
				"descriptors": [
					{
						"label": "Violence",
						"image": null
					}
				],
				"disclaimers": [

				]
			},
			"childDownloadTypes": null,
			"genres": [
				{
					"label": "Action & Adventure"
				},
				{
					"label": "Racing & Flying"
				}
			],
			"image": "http://download.xbox.com/content/images/66acd000-77fe-1000-9115-d802545107f4/1033/boxartlg.jpg",
			"url": "/en-US/X8/Game/00000000-0000-400b-80bf-0001545107f4",
			"downloadTypeClass": "GameVideo",
			"downloadTypeText": "Video",
			"platform": "Xbox",
			"price": {
				"goldPrice": "Free",
				"silverPrice": "Free"
			},
			"prices": [
				{
					"method": "currency",
					"amount": 0,
					"display": "Free",
					"tax": "plus tax",
					"user": "silver"
				}
			]
		},
		{
			"id": "00000000-0000-400c-80cf-0002545107f4",
			"title": "Stuntman Vehicle Pack",
			"description": "Rev up your experience with these additional vehicles for Multiplayer and Constructor! There are no refunds for this item. For more information, see www.xbox.com/live/accounts.",
			"userRating": {
				"allowed": true,
				"current": {
					"Aggregate": 3.75,
					"Count": 49
				}
			},
			"originalReleaseDate": "/Date(1198054800000)/",
			"contentRating": {
				"label": "T (Teen)",
				"image": "http://epix.xbox.com/consoleassets/vm_ems/DetailsPages/RatingSystemID/0/default/Values/30.png",
				"age": 13,
				"purchaseAgeGate": false,
				"videoAgeGate": false,
				"descriptors": [
					{
						"label": "Violence",
						"image": null
					}
				],
				"disclaimers": [

				]
			},
			"childDownloadTypes": null,
			"genres": [
				{
					"label": "Action & Adventure"
				},
				{
					"label": "Racing & Flying"
				}
			],
			"image": "http://download.xbox.com/content/images/66acd000-77fe-1000-9115-d802545107f4/1033/boxartlg.jpg",
			"url": "/en-US/X8/Game/00000000-0000-400c-80cf-0002545107f4",
			"downloadTypeClass": "GameAddon",
			"downloadTypeText": "Add-on",
			"platform": "Xbox",
			"price": {
				"goldPrice": "$4.99",
				"silverPrice": "$4.99"
			},
			"prices": [
				{
					"method": "currency",
					"amount": 4.99,
					"display": "$4.99",
					"tax": "plus tax",
					"user": "silver"
				}
			]
		},
		{
			"id": "00000000-0000-4002-802f-0003545107f4",
			"title": "Stuntman Vehicle Picture Pack 1",
			"description": "Drive your way onto the big-screen with the vehicles of Stuntman: Ignition in this 6 picture pack. There are no refunds for this item. For more information, see www.xbox.com/live/accounts.",
			"userRating": {
				"allowed": true,
				"current": {
					"Aggregate": 3.75,
					"Count": 32
				}
			},
			"originalReleaseDate": "/Date(1196413200000)/",
			"contentRating": null,
			"childDownloadTypes": null,
			"genres": [
				{
					"label": "Action & Adventure"
				},
				{
					"label": "Racing & Flying"
				}
			],
			"image": "http://download.xbox.com/content/images/66acd000-77fe-1000-9115-d802545107f4/1033/boxartlg.jpg",
			"url": "/en-US/X8/Game/00000000-0000-4002-802f-0003545107f4",
			"downloadTypeClass": "GamerPic",
			"downloadTypeText": "GamerPic",
			"platform": "Xbox",
			"price": {
				"goldPrice": "$1.49",
				"silverPrice": "$1.49"
			},
			"prices": [
				{
					"method": "currency",
					"amount": 1.49,
					"display": "$1.49",
					"tax": "plus tax",
					"user": "silver"
				}
			]
		},
		{
			"id": "00000000-0000-4002-802f-0004545107f4",
			"title": "Stuntman Vehicle Picture Pack 2",
			"description": "Drive your way onto the big-screen with the vehicles of Stuntman: Ignition in this 6 picture pack. There are no refunds for this item. For more information, see www.xbox.com/live/accounts.",
			"userRating": {
				"allowed": true,
				"current": {
					"Aggregate": 4,
					"Count": 30
				}
			},
			"originalReleaseDate": "/Date(1196413200000)/",
			"contentRating": null,
			"childDownloadTypes": null,
			"genres": [
				{
					"label": "Action & Adventure"
				},
				{
					"label": "Racing & Flying"
				}
			],
			"image": "http://download.xbox.com/content/images/66acd000-77fe-1000-9115-d802545107f4/1033/boxartlg.jpg",
			"url": "/en-US/X8/Game/00000000-0000-4002-802f-0004545107f4",
			"downloadTypeClass": "GamerPic",
			"downloadTypeText": "GamerPic",
			"platform": "Xbox",
			"price": {
				"goldPrice": "$1.49",
				"silverPrice": "$1.49"
			},
			"prices": [
				{
					"method": "currency",
					"amount": 1.49,
					"display": "$1.49",
					"tax": "plus tax",
					"user": "silver"
				}
			]
		}
	]
}
