{
	"version": "1",
	"id": "66acd000-77fe-1000-9115-d80258410b34",
	"title": "Haunt",
	"image": "http://download.xbox.com/content/images/66acd000-77fe-1000-9115-d80258410b34/1033/boxartlg.jpg",
	"backgroundImage": "http://download.xbox.com/content/images/66acd000-77fe-1000-9115-d80258410b34/1033/background.jpg",
	"downloadTypeClass": "Game",
	"downloadTypeText": "Game",
	"platform": "Xbox",
	"description": "Welcome to Benjy's Mansion - a spooky haunted house where you are the first visitor for a generation! Haunt leverages the power of Kinect to enable you to freely explore the house using just your body as the controller - you'll need to stay on your toes in order to outsmart the mansion's host of fiendish ghosts and unravel the sinister secrets that shroud the mansion in mystery!",
	"genres": [
		{
			"label": "Action & Adventure"
		},
		{
			"label": "Family"
		},
		{
			"label": "Kinect"
		}
	],
	"publisher": "Microsoft Studios",
	"studio": "NanaOn-Sha co., ltd.",
	"originalReleaseDate": "/Date(1317340800000)/",
	"contentRating": {
		"label": "E10 (Everyone 10+)",
		"image": "http://epix.xbox.com/consoleassets/vm_ems/DetailsPages/RatingSystemID/0/default/Values/20.png",
		"age": 10,
		"purchaseAgeGate": false,
		"videoAgeGate": false,
		"descriptors": [
			{
				"label": "Fantasy Violence",
				"image": null
			}
		],
		"disclaimers": [

		]
	},
	"trailers": [

	],
	"gameManual": null,
	"screenshots": [
		"http://download.xbox.com/content/images/66acd000-77fe-1000-9115-d80258410b34/1033/screenlg1.jpg",
		"http://download.xbox.com/content/images/66acd000-77fe-1000-9115-d80258410b34/1033/screenlg2.jpg",
		"http://download.xbox.com/content/images/66acd000-77fe-1000-9115-d80258410b34/1033/screenlg3.jpg",
		"http://download.xbox.com/content/images/66acd000-77fe-1000-9115-d80258410b34/1033/screenlg4.jpg",
		"http://download.xbox.com/content/images/66acd000-77fe-1000-9115-d80258410b34/1033/screenlg5.jpg",
		"http://download.xbox.com/content/images/66acd000-77fe-1000-9115-d80258410b34/1033/screenlg6.jpg",
		"http://download.xbox.com/content/images/66acd000-77fe-1000-9115-d80258410b34/1033/screenlg7.jpg",
		"http://download.xbox.com/content/images/66acd000-77fe-1000-9115-d80258410b34/1033/screenlg8.jpg",
		"http://download.xbox.com/content/images/66acd000-77fe-1000-9115-d80258410b34/1033/screenlg9.jpg",
		"http://download.xbox.com/content/images/66acd000-77fe-1000-9115-d80258410b34/1033/screenlg10.jpg",
		"http://download.xbox.com/content/images/66acd000-77fe-1000-9115-d80258410b34/1033/screenlg11.jpg",
		"http://download.xbox.com/content/images/66acd000-77fe-1000-9115-d80258410b34/1033/screenlg12.jpg"
	],
	"detailsUrl": "/en-US/Product/Haunt/66acd000-77fe-1000-9115-d80258410b34",
	"userRating": {
		"allowed": true,
		"current": {
			"Aggregate": 3.5,
			"Count": 13303
		}
	},
	"price": {
		"goldPrice": "$9.99",
		"silverPrice": "$9.99"
	},
	"prices": [
		{
			"method": "currency",
			"amount": 9.99,
			"display": "$9.99",
			"tax": "plus tax",
			"user": "silver"
		}
	],
	"childDownloadTypes": [
		"Game",
		"GameDemo",
		"GameVideo"
	],
	"childDownloadsUrl": "/en-US/X8/Game/66acd000-77fe-1000-9115-d80258410b34/Children",
	"childDownloads": [
		{
			"id": "7312fa7a-7c7a-4395-8d02-0d60e76cc2df",
			"title": "Trial Game - Haunt",
			"description": "Welcome to Benjy's Mansion - a spooky haunted house where you are the first visitor for a generation! Haunt leverages the power of Kinect to enable you to freely explore the house using just your body as the controller - you'll need to stay on your toes in order to outsmart the mansion's host of fiendish ghosts and unravel the sinister secrets that shroud the mansion in mystery!",
			"userRating": {
				"allowed": false,
				"current": {
					"Aggregate": 0,
					"Count": 0
				}
			},
			"originalReleaseDate": "/Date(1326877200000)/",
			"contentRating": {
				"label": "E10 (Everyone 10+)",
				"image": "http://epix.xbox.com/consoleassets/vm_ems/DetailsPages/RatingSystemID/0/default/Values/20.png",
				"age": 10,
				"purchaseAgeGate": false,
				"videoAgeGate": false,
				"descriptors": [
					{
						"label": "Fantasy Violence",
						"image": null
					}
				],
				"disclaimers": [

				]
			},
			"childDownloadTypes": null,
			"genres": [
				{
					"label": "Action & Adventure"
				},
				{
					"label": "Family"
				},
				{
					"label": "Kinect"
				}
			],
			"image": "http://download.xbox.com/content/images/7312fa7a-7c7a-4395-8d02-0d60e76cc2df/1033/boxartlg.jpg",
			"url": "/en-US/X8/Game/7312fa7a-7c7a-4395-8d02-0d60e76cc2df",
			"downloadTypeClass": "GameDemo",
			"downloadTypeText": "Demo",
			"platform": "Xbox",
			"price": {
				"goldPrice": "Free",
				"silverPrice": "Free"
			},
			"prices": [
				{
					"method": "currency",
					"amount": 0,
					"display": "Free",
					"tax": "plus tax",
					"user": "silver"
				}
			]
		},
		{
			"id": "66acd000-77fe-1000-9115-d80258410b34",
			"title": "Haunt",
			"description": "Welcome to Benjy's Mansion - a spooky haunted house where you are the first visitor for a generation! Haunt leverages the power of Kinect to enable you to freely explore the house using just your body as the controller - you'll need to stay on your toes in order to outsmart the mansion's host of fiendish ghosts and unravel the sinister secrets that shroud the mansion in mystery!",
			"userRating": {
				"allowed": true,
				"current": {
					"Aggregate": 3.5,
					"Count": 13303
				}
			},
			"originalReleaseDate": "/Date(1326877200000)/",
			"contentRating": {
				"label": "E10 (Everyone 10+)",
				"image": "http://epix.xbox.com/consoleassets/vm_ems/DetailsPages/RatingSystemID/0/default/Values/20.png",
				"age": 10,
				"purchaseAgeGate": false,
				"videoAgeGate": false,
				"descriptors": [
					{
						"label": "Fantasy Violence",
						"image": null
					}
				],
				"disclaimers": [

				]
			},
			"childDownloadTypes": [
				"Game",
				"GameDemo",
				"GameVideo"
			],
			"genres": [
				{
					"label": "Action & Adventure"
				},
				{
					"label": "Family"
				},
				{
					"label": "Kinect"
				}
			],
			"image": "http://download.xbox.com/content/images/66acd000-77fe-1000-9115-d80258410b34/1033/boxartlg.jpg",
			"url": "/en-US/X8/Game/66acd000-77fe-1000-9115-d80258410b34",
			"downloadTypeClass": "Game",
			"downloadTypeText": "Game",
			"platform": "Xbox",
			"price": {
				"goldPrice": "$9.99",
				"silverPrice": "$9.99"
			},
			"prices": [
				{
					"method": "currency",
					"amount": 9.99,
					"display": "$9.99",
					"tax": "plus tax",
					"user": "silver"
				}
			]
		},
		{
			"id": "85cd9c82-15ce-4e7d-ba6f-5a4be408c2e5",
			"title": "Haunt - Trailer",
			"description": "Welcome to Benjy's Mansion - a spooky haunted house where you are the first visitor for a generation! Haunt leverages the power of Kinect to enable you to freely explore the house using just your body as the controller - you'll need to stay on your toes in order to outsmart the mansion's host of fiendish ghosts and unravel the sinister secrets that shroud the mansion in mystery!",
			"userRating": {
				"allowed": true,
				"current": {
					"Aggregate": 3.75,
					"Count": 622
				}
			},
			"originalReleaseDate": "/Date(1316163600000)/",
			"contentRating": {
				"label": "E10 (Everyone 10+)",
				"image": "http://epix.xbox.com/consoleassets/vm_ems/DetailsPages/RatingSystemID/0/default/Values/20.png",
				"age": 10,
				"purchaseAgeGate": false,
				"videoAgeGate": false,
				"descriptors": [
					{
						"label": "Fantasy Violence",
						"image": null
					}
				],
				"disclaimers": [

				]
			},
			"childDownloadTypes": null,
			"genres": [
				{
					"label": "Action & Adventure"
				},
				{
					"label": "Family"
				},
				{
					"label": "Kinect"
				}
			],
			"image": "http://download.xbox.com/content/images/66acd000-77fe-1000-9115-d80258410b34/1033/boxartlg.jpg",
			"url": "/en-US/X8/Game/85cd9c82-15ce-4e7d-ba6f-5a4be408c2e5",
			"downloadTypeClass": "GameVideo",
			"downloadTypeText": "Video",
			"platform": "Xbox",
			"price": {
				"goldPrice": "Free",
				"silverPrice": "Free"
			},
			"prices": [
				{
					"method": "currency",
					"amount": 0,
					"display": "Free",
					"tax": "plus tax",
					"user": "silver"
				}
			]
		}
	]
}
