{
    "version": "1",
    "id": "66acd000-77fe-1000-9115-d802415608fa",
    "title": "Cabela's® AfricanAdv",
    "image": "http://download.xbox.com/content/images/66acd000-77fe-1000-9115-d802415608fa/1033/boxartlg.jpg",
    "backgroundImage": "http://download.xbox.com/content/images/66acd000-77fe-1000-9115-d802415608fa/1033/background.jpg",
    "downloadTypeClass": "Game",
    "downloadTypeText": "Game",
    "platform": "Xbox",
    "description": "The Games on Demand version supports English.  Explore the vast wilderness of Africa on foot and by vehicle, where you’ll go head to head with the most ferocious beasts on the planet as you attempt to take down the biggest of the ‘Big 5”; The Rhino, Lion, Leopard, Cape Buffalo & African Elephant!  • Features vast hunting areas 5x the size of any other Cabela’s® console game • Highly memorable ‘Big 5’; challenging and fun boss animal fights.  • All-new, exciting storyline to explore • Capabilities to enter and leave your vehicle anytime, anywhere while you take on large herds of stampeding buffalo, packs of predators, and dream prey across 5 different biomes!  • There are two exciting modes: Safari Mode: mission-based career progression, Shooting Galleries: supports TOP SHOT ELITE and TOP SHOT FEARMASTER peripherals.  • A wide selection of firearms and load-outs to stalk, dodge, and grapple with the most ferocious beasts alive.",
    "genres": [
        {
            "label": "Shooter"
        }
    ],
    "publisher": "Activision",
    "studio": "Cauldron",
    "originalReleaseDate": "/Date(1381795200000)/",
    "contentRating": {
        "label": "T (Teen)",
        "image": "http://epix.xbox.com/consoleassets/vm_ems/DetailsPages/RatingSystemID/0/default/Values/30.png",
        "age": 13,
        "purchaseAgeGate": false,
        "videoAgeGate": false,
        "descriptors": [
            {
                "label": "Blood",
                "image": null
            },
            {
                "label": "Violence",
                "image": null
            }
        ],
        "disclaimers": [

        ]
    },
    "trailers": [

    ],
    "gameManual": null,
    "screenshots": [
        "http://download.xbox.com/content/images/66acd000-77fe-1000-9115-d802415608fa/1033/screenlg1.jpg",
        "http://download.xbox.com/content/images/66acd000-77fe-1000-9115-d802415608fa/1033/screenlg2.jpg",
        "http://download.xbox.com/content/images/66acd000-77fe-1000-9115-d802415608fa/1033/screenlg3.jpg",
        "http://download.xbox.com/content/images/66acd000-77fe-1000-9115-d802415608fa/1033/screenlg4.jpg",
        "http://download.xbox.com/content/images/66acd000-77fe-1000-9115-d802415608fa/1033/screenlg5.jpg",
        "http://download.xbox.com/content/images/66acd000-77fe-1000-9115-d802415608fa/1033/screenlg6.jpg",
        "http://download.xbox.com/content/images/66acd000-77fe-1000-9115-d802415608fa/1033/screenlg7.jpg",
        "http://download.xbox.com/content/images/66acd000-77fe-1000-9115-d802415608fa/1033/screenlg8.jpg"
    ],
    "detailsUrl": "/en-US/Product/Cabelas-AfricanAdv/66acd000-77fe-1000-9115-d802415608fa",
    "userRating": {
        "allowed": true,
        "current": {
            "Aggregate": 3.5,
            "Count": 647
        }
    },
    "price": {
        "goldPrice": "$39.99",
        "silverPrice": "$39.99"
    },
    "prices": [
        {
            "method": "currency",
            "amount": 39.99,
            "display": "$39.99",
            "tax": "plus tax",
            "user": "silver"
        }
    ],
    "childDownloadTypes": [
        "Game"
    ],
    "childDownloadsUrl": "/en-US/X8/Game/66acd000-77fe-1000-9115-d802415608fa/Children",
    "childDownloads": [
        {
            "id": "66acd000-77fe-1000-9115-d802415608fa",
            "title": "Cabela's® AfricanAdv",
            "description": "The Games on Demand version supports English.  Explore the vast wilderness of Africa on foot and by vehicle, where you’ll go head to head with the most ferocious beasts on the planet as you attempt to take down the biggest of the ‘Big 5”; The Rhino, Lion, Leopard, Cape Buffalo & African Elephant!  • Features vast hunting areas 5x the size of any other Cabela’s® console game • Highly memorable ‘Big 5’; challenging and fun boss animal fights.  • All-new, exciting storyline to explore • Capabilities to enter and leave your vehicle anytime, anywhere while you take on large herds of stampeding buffalo, packs of predators, and dream prey across 5 different biomes!  • There are two exciting modes: Safari Mode: mission-based career progression, Shooting Galleries: supports TOP SHOT ELITE and TOP SHOT FEARMASTER peripherals.  • A wide selection of firearms and load-outs to stalk, dodge, and grapple with the most ferocious beasts alive.",
            "userRating": {
                "allowed": true,
                "current": {
                    "Aggregate": 3.5,
                    "Count": 647
                }
            },
            "originalReleaseDate": "/Date(1382691600000)/",
            "contentRating": {
                "label": "T (Teen)",
                "image": "http://epix.xbox.com/consoleassets/vm_ems/DetailsPages/RatingSystemID/0/default/Values/30.png",
                "age": 13,
                "purchaseAgeGate": false,
                "videoAgeGate": false,
                "descriptors": [
                    {
                        "label": "Blood",
                        "image": null
                    },
                    {
                        "label": "Violence",
                        "image": null
                    }
                ],
                "disclaimers": [

                ]
            },
            "childDownloadTypes": [
                "Game"
            ],
            "genres": [
                {
                    "label": "Shooter"
                }
            ],
            "image": "http://download.xbox.com/content/images/66acd000-77fe-1000-9115-d802415608fa/1033/boxartlg.jpg",
            "url": "/en-US/X8/Game/66acd000-77fe-1000-9115-d802415608fa",
            "downloadTypeClass": "Game",
            "downloadTypeText": "Game",
            "platform": "Xbox",
            "price": {
                "goldPrice": "$39.99",
                "silverPrice": "$39.99"
            },
            "prices": [
                {
                    "method": "currency",
                    "amount": 39.99,
                    "display": "$39.99",
                    "tax": "plus tax",
                    "user": "silver"
                }
            ]
        }
    ]
}
