{
	"version": "1",
	"id": "66acd000-77fe-1000-9115-d8025451085e",
	"title": "Fantastic Pets",
	"image": "http://download.xbox.com/content/images/66acd000-77fe-1000-9115-d8025451085e/1033/boxartlg.jpg",
	"backgroundImage": "http://download.xbox.com/content/images/66acd000-77fe-1000-9115-d8025451085e/1033/background.jpg",
	"downloadTypeClass": "Game",
	"downloadTypeText": "Game",
	"platform": "Xbox",
	"description": "The Games on Demand version supports  English, French, Italian, German, Spanish, Dutch.  Your uncle Doctor Menagerie is away on expedition and needs you to look after his Fantastic Pets. Take fire breathing dogs, flying ponies, horned cats and furry lizards home with you today (and more normal pets too). You appear on-screen with your pet to give them commands, take photos, play with a friend, enter Talent Shows and loads more. Plus, every pet can be customized in hundreds of ways. Welcome to the world of Fantastic Pets!",
	"genres": [
		{
			"label": "Family"
		},
		{
			"label": "Kinect"
		}
	],
	"publisher": "THQ Inc.",
	"studio": "Blitz Games Studios Ltd.",
	"originalReleaseDate": "/Date(1299542400000)/",
	"contentRating": {
		"label": "E (Everyone)",
		"image": "http://epix.xbox.com/consoleassets/vm_ems/DetailsPages/RatingSystemID/0/default/Values/10.png",
		"age": 6,
		"purchaseAgeGate": false,
		"videoAgeGate": false,
		"descriptors": [

		],
		"disclaimers": [

		]
	},
	"trailers": [

	],
	"gameManual": "http://download.xbox.com/content/5451085e/FantasticPets_Manual_EN_Revised.pdf",
	"screenshots": [
		"http://download.xbox.com/content/images/66acd000-77fe-1000-9115-d8025451085e/1033/screenlg1.jpg",
		"http://download.xbox.com/content/images/66acd000-77fe-1000-9115-d8025451085e/1033/screenlg2.jpg",
		"http://download.xbox.com/content/images/66acd000-77fe-1000-9115-d8025451085e/1033/screenlg3.jpg",
		"http://download.xbox.com/content/images/66acd000-77fe-1000-9115-d8025451085e/1033/screenlg4.jpg",
		"http://download.xbox.com/content/images/66acd000-77fe-1000-9115-d8025451085e/1033/screenlg5.jpg",
		"http://download.xbox.com/content/images/66acd000-77fe-1000-9115-d8025451085e/1033/screenlg6.jpg",
		"http://download.xbox.com/content/images/66acd000-77fe-1000-9115-d8025451085e/1033/screenlg7.jpg",
		"http://download.xbox.com/content/images/66acd000-77fe-1000-9115-d8025451085e/1033/screenlg8.jpg",
		"http://download.xbox.com/content/images/66acd000-77fe-1000-9115-d8025451085e/1033/screenlg9.jpg",
		"http://download.xbox.com/content/images/66acd000-77fe-1000-9115-d8025451085e/1033/screenlg10.jpg",
		"http://download.xbox.com/content/images/66acd000-77fe-1000-9115-d8025451085e/1033/screenlg11.jpg"
	],
	"detailsUrl": "/en-US/Product/Fantastic-Pets/66acd000-77fe-1000-9115-d8025451085e",
	"userRating": {
		"allowed": true,
		"current": {
			"Aggregate": 3.75,
			"Count": 13145
		}
	},
	"price": {
		"goldPrice": "$19.99",
		"silverPrice": "$19.99"
	},
	"prices": [
		{
			"method": "currency",
			"amount": 19.99,
			"display": "$19.99",
			"tax": "plus tax",
			"user": "silver"
		}
	],
	"childDownloadTypes": [
		"Game",
		"GameDemo",
		"GameVideo",
		"GameAddon"
	],
	"childDownloadsUrl": "/en-US/X8/Game/66acd000-77fe-1000-9115-d8025451085e/Children",
	"childDownloads": [
		{
			"id": "66acd000-77fe-1000-9115-d8025451085e",
			"title": "Fantastic Pets",
			"description": "The Games on Demand version supports  English, French, Italian, German, Spanish, Dutch.  Your uncle Doctor Menagerie is away on expedition and needs you to look after his Fantastic Pets. Take fire breathing dogs, flying ponies, horned cats and furry lizards home with you today (and more normal pets too). You appear on-screen with your pet to give them commands, take photos, play with a friend, enter Talent Shows and loads more. Plus, every pet can be customized in hundreds of ways. Welcome to the world of Fantastic Pets!",
			"userRating": {
				"allowed": true,
				"current": {
					"Aggregate": 3.75,
					"Count": 13145
				}
			},
			"originalReleaseDate": "/Date(1332838800000)/",
			"contentRating": {
				"label": "E (Everyone)",
				"image": "http://epix.xbox.com/consoleassets/vm_ems/DetailsPages/RatingSystemID/0/default/Values/10.png",
				"age": 6,
				"purchaseAgeGate": false,
				"videoAgeGate": false,
				"descriptors": [

				],
				"disclaimers": [

				]
			},
			"childDownloadTypes": [
				"Game",
				"GameDemo",
				"GameVideo",
				"GameAddon"
			],
			"genres": [
				{
					"label": "Family"
				},
				{
					"label": "Kinect"
				}
			],
			"image": "http://download.xbox.com/content/images/66acd000-77fe-1000-9115-d8025451085e/1033/boxartlg.jpg",
			"url": "/en-US/X8/Game/66acd000-77fe-1000-9115-d8025451085e",
			"downloadTypeClass": "Game",
			"downloadTypeText": "Game",
			"platform": "Xbox",
			"price": {
				"goldPrice": "$19.99",
				"silverPrice": "$19.99"
			},
			"prices": [
				{
					"method": "currency",
					"amount": 19.99,
					"display": "$19.99",
					"tax": "plus tax",
					"user": "silver"
				}
			]
		},
		{
			"id": "98ca7ad6-274e-4ed9-8626-fda641e06a7a",
			"title": "Fantastic Pets - Game Trailer",
			"description": "Fantastic Pets is the only video game that lets players create the pet of their dreams – real or fantastical!  Selecting from four different animal species – dog, cat, lizard or horse – players can customize and create countless variations of pets to nurture, train and play with.  For the first time ever players can join their pets on-screen and play together as if their pets were real, living creatures using augmented reality technology on the Microsoft Kinect.  Players can use both voice and full-body commands to nurture, play, train and grow closer to his or her animal friend. Players compete in Talent Shows to level up their Pet Trainer to unlock new customization options, accessories and achievements!   ",
			"userRating": {
				"allowed": true,
				"current": {
					"Aggregate": 3.75,
					"Count": 330
				}
			},
			"originalReleaseDate": "/Date(1301994000000)/",
			"contentRating": {
				"label": "E (Everyone)",
				"image": "http://epix.xbox.com/consoleassets/vm_ems/DetailsPages/RatingSystemID/0/default/Values/10.png",
				"age": 6,
				"purchaseAgeGate": false,
				"videoAgeGate": false,
				"descriptors": [

				],
				"disclaimers": [

				]
			},
			"childDownloadTypes": null,
			"genres": [
				{
					"label": "Family"
				},
				{
					"label": "Kinect"
				}
			],
			"image": "http://download.xbox.com/content/images/66acd000-77fe-1000-9115-d8025451085e/1033/boxartlg.jpg",
			"url": "/en-US/X8/Game/98ca7ad6-274e-4ed9-8626-fda641e06a7a",
			"downloadTypeClass": "GameVideo",
			"downloadTypeText": "Video",
			"platform": "Xbox",
			"price": {
				"goldPrice": "Free",
				"silverPrice": "Free"
			},
			"prices": [
				{
					"method": "currency",
					"amount": 0,
					"display": "Free",
					"tax": "plus tax",
					"user": "silver"
				}
			]
		},
		{
			"id": "66acd000-77fe-1000-9115-d80254518892",
			"title": "Fantastic Pets Demo",
			"description": "Fantastic Pets is the only video game that lets players create the pet of their dreams – real or fantastical!  Selecting from four different animal species – dog, cat, lizard or horse – players can customize and create countless variations of pets to nurture, train and play with.  For the first time ever players can join their pets on-screen and play together as if their pets were real, living creatures using augmented reality technology on the Microsoft Kinect.  Players can use both voice and full-body commands to nurture, play, train and grow closer to his or her animal friend. Players compete in Talent Shows to level up their Pet Trainer to unlock new customization options, accessories and achievements!   ",
			"userRating": {
				"allowed": true,
				"current": {
					"Aggregate": 3.5,
					"Count": 1970
				}
			},
			"originalReleaseDate": "/Date(1302886800000)/",
			"contentRating": {
				"label": "E (Everyone)",
				"image": "http://epix.xbox.com/consoleassets/vm_ems/DetailsPages/RatingSystemID/0/default/Values/10.png",
				"age": 6,
				"purchaseAgeGate": false,
				"videoAgeGate": false,
				"descriptors": [

				],
				"disclaimers": [

				]
			},
			"childDownloadTypes": null,
			"genres": [
				{
					"label": "Family"
				},
				{
					"label": "Kinect"
				}
			],
			"image": "http://download.xbox.com/content/images/66acd000-77fe-1000-9115-d80254518892/1033/boxartlg.jpg",
			"url": "/en-US/X8/Game/66acd000-77fe-1000-9115-d80254518892",
			"downloadTypeClass": "GameDemo",
			"downloadTypeText": "Demo",
			"platform": "Xbox",
			"price": {
				"goldPrice": "Free",
				"silverPrice": "Free"
			},
			"prices": [
				{
					"method": "currency",
					"amount": 0,
					"display": "Free",
					"tax": "plus tax",
					"user": "silver"
				}
			]
		},
		{
			"id": "7c886328-3b95-4c45-bc60-26b8c4cad2fb",
			"title": "The Fantastic Pets flight pack ",
			"description": "Take to the skies with new customization options and a brand new activity. This pack includes new wings and new patterns to customize your pet in the pet database, then guide your pet through the clouds in the new 'Take Off!' activity. ",
			"userRating": {
				"allowed": true,
				"current": {
					"Aggregate": 3.5,
					"Count": 353
				}
			},
			"originalReleaseDate": "/Date(1304413200000)/",
			"contentRating": {
				"label": "E (Everyone)",
				"image": "http://epix.xbox.com/consoleassets/vm_ems/DetailsPages/RatingSystemID/0/default/Values/10.png",
				"age": 6,
				"purchaseAgeGate": false,
				"videoAgeGate": false,
				"descriptors": [

				],
				"disclaimers": [

				]
			},
			"childDownloadTypes": null,
			"genres": [
				{
					"label": "Family"
				},
				{
					"label": "Kinect"
				}
			],
			"image": "http://download.xbox.com/content/images/7c886328-3b95-4c45-bc60-26b8c4cad2fb/1033/boxartlg.jpg",
			"url": "/en-US/X8/Game/7c886328-3b95-4c45-bc60-26b8c4cad2fb",
			"downloadTypeClass": "GameAddon",
			"downloadTypeText": "Add-on",
			"platform": "Xbox",
			"price": {
				"goldPrice": "$2.99",
				"silverPrice": "$2.99"
			},
			"prices": [
				{
					"method": "currency",
					"amount": 2.99,
					"display": "$2.99",
					"tax": "plus tax",
					"user": "silver"
				}
			]
		}
	]
}
