{
	"version": "1",
	"id": "66acd000-77fe-1000-9115-d802584111e8",
	"title": "State of Decay",
	"image": "http://download.xbox.com/content/images/66acd000-77fe-1000-9115-d802584111e8/1033/boxartlg.jpg",
	"backgroundImage": "http://download.xbox.com/content/images/66acd000-77fe-1000-9115-d802584111e8/1033/background.jpg",
	"downloadTypeClass": "Game",
	"downloadTypeText": "Game",
	"platform": "Xbox",
	"description": "The end is here. Life as you knew it has gone to hell after the mother of all zombie outbreaks. Now you and the few scattered survivors must band together to survive and rebuild in a 3rd-person action game set in a dynamic open world. You choose where to make your stand, designing and fortifying your home base, performing daring raids for food and ammunition, and rescuing other playable survivors with unique talents.",
	"genres": [
		{
			"label": "Action & Adventure"
		},
		{
			"label": "Strategy & Simulation"
		}
	],
	"publisher": "Microsoft Studios",
	"studio": "Undead Labs",
	"originalReleaseDate": null,
	"contentRating": {
		"label": "M (Mature)",
		"image": "http://epix.xbox.com/consoleassets/vm_ems/DetailsPages/RatingSystemID/0/default/Values/40.png",
		"age": 17,
		"purchaseAgeGate": true,
		"videoAgeGate": true,
		"descriptors": [
			{
				"label": "Blood and Gore",
				"image": null
			},
			{
				"label": "Drug Reference",
				"image": null
			},
			{
				"label": "Intense Violence",
				"image": null
			},
			{
				"label": "Partial Nudity",
				"image": null
			},
			{
				"label": "Sexual Themes",
				"image": null
			},
			{
				"label": "Strong Language",
				"image": null
			}
		],
		"disclaimers": [
			"Online Interactions Not Rated by the ESRB"
		]
	},
	"trailers": [

	],
	"gameManual": null,
	"screenshots": [
		"http://download.xbox.com/content/images/66acd000-77fe-1000-9115-d802584111e8/1033/screenlg1.jpg",
		"http://download.xbox.com/content/images/66acd000-77fe-1000-9115-d802584111e8/1033/screenlg2.jpg",
		"http://download.xbox.com/content/images/66acd000-77fe-1000-9115-d802584111e8/1033/screenlg3.jpg",
		"http://download.xbox.com/content/images/66acd000-77fe-1000-9115-d802584111e8/1033/screenlg5.jpg",
		"http://download.xbox.com/content/images/66acd000-77fe-1000-9115-d802584111e8/1033/screenlg6.jpg",
		"http://download.xbox.com/content/images/66acd000-77fe-1000-9115-d802584111e8/1033/screenlg7.jpg",
		"http://download.xbox.com/content/images/66acd000-77fe-1000-9115-d802584111e8/1033/screenlg8.jpg",
		"http://download.xbox.com/content/images/66acd000-77fe-1000-9115-d802584111e8/1033/screenlg9.jpg",
		"http://download.xbox.com/content/images/66acd000-77fe-1000-9115-d802584111e8/1033/screenlg10.jpg",
		"http://download.xbox.com/content/images/66acd000-77fe-1000-9115-d802584111e8/1033/screenlg11.jpg",
		"http://download.xbox.com/content/images/66acd000-77fe-1000-9115-d802584111e8/1033/screenlg13.jpg"
	],
	"detailsUrl": "/en-US/Product/State-of-Decay/66acd000-77fe-1000-9115-d802584111e8",
	"userRating": {
		"allowed": true,
		"current": {
			"Aggregate": 4.5,
			"Count": 77950
		}
	},
	"price": {
		"goldPrice": "$19.99",
		"silverPrice": "$19.99"
	},
	"prices": [
		{
			"method": "currency",
			"amount": 19.99,
			"display": "$19.99",
			"tax": "plus tax",
			"user": "silver"
		}
	],
	"childDownloadTypes": [
		"Game",
		"GameDemo",
		"GameVideo",
		"GameAddon"
	],
	"childDownloadsUrl": "/en-US/X8/Game/66acd000-77fe-1000-9115-d802584111e8/Children",
	"childDownloads": [
		{
			"id": "f6da3d88-67ff-4a51-afb7-b48a5a3e606f",
			"title": "Breakdown Trailer",
			"description": "Download this trailer.",
			"userRating": {
				"allowed": true,
				"current": {
					"Aggregate": 4.25,
					"Count": 154
				}
			},
			"originalReleaseDate": "/Date(1385715600000)/",
			"contentRating": {
				"label": "M (Mature)",
				"image": "http://epix.xbox.com/consoleassets/vm_ems/DetailsPages/RatingSystemID/0/default/Values/40.png",
				"age": 17,
				"purchaseAgeGate": true,
				"videoAgeGate": true,
				"descriptors": [
					{
						"label": "Blood and Gore",
						"image": null
					},
					{
						"label": "Drug Reference",
						"image": null
					},
					{
						"label": "Intense Violence",
						"image": null
					},
					{
						"label": "Partial Nudity",
						"image": null
					},
					{
						"label": "Sexual Themes",
						"image": null
					},
					{
						"label": "Strong Language",
						"image": null
					}
				],
				"disclaimers": [

				]
			},
			"childDownloadTypes": null,
			"genres": [
				{
					"label": "Action & Adventure"
				},
				{
					"label": "Strategy & Simulation"
				}
			],
			"image": "http://download.xbox.com/content/images/66acd000-77fe-1000-9115-d802584111e8/1033/boxartlg.jpg",
			"url": "/en-US/X8/Game/f6da3d88-67ff-4a51-afb7-b48a5a3e606f",
			"downloadTypeClass": "GameVideo",
			"downloadTypeText": "Video",
			"platform": "Xbox",
			"price": {
				"goldPrice": "Free",
				"silverPrice": "Free"
			},
			"prices": [
				{
					"method": "currency",
					"amount": 0,
					"display": "Free",
					"tax": "plus tax",
					"user": "silver"
				}
			]
		},
		{
			"id": "ab78bce2-0fd1-4ca5-aa8a-419ebcc57ae0",
			"title": "Lifeline Trailer",
			"description": "Download this trailer.",
			"userRating": {
				"allowed": true,
				"current": {
					"Aggregate": 4.5,
					"Count": 128
				}
			},
			"originalReleaseDate": "/Date(1401267600000)/",
			"contentRating": {
				"label": "M (Mature)",
				"image": "http://epix.xbox.com/consoleassets/vm_ems/DetailsPages/RatingSystemID/0/default/Values/40.png",
				"age": 17,
				"purchaseAgeGate": true,
				"videoAgeGate": true,
				"descriptors": [
					{
						"label": "Blood and Gore",
						"image": null
					},
					{
						"label": "Drug Reference",
						"image": null
					},
					{
						"label": "Intense Violence",
						"image": null
					},
					{
						"label": "Partial Nudity",
						"image": null
					},
					{
						"label": "Sexual Themes",
						"image": null
					},
					{
						"label": "Strong Language",
						"image": null
					}
				],
				"disclaimers": [

				]
			},
			"childDownloadTypes": null,
			"genres": [
				{
					"label": "Action & Adventure"
				},
				{
					"label": "Strategy & Simulation"
				}
			],
			"image": "http://download.xbox.com/content/images/66acd000-77fe-1000-9115-d802584111e8/1033/boxartlg.jpg",
			"url": "/en-US/X8/Game/ab78bce2-0fd1-4ca5-aa8a-419ebcc57ae0",
			"downloadTypeClass": "GameVideo",
			"downloadTypeText": "Video",
			"platform": "Xbox",
			"price": {
				"goldPrice": "Free",
				"silverPrice": "Free"
			},
			"prices": [
				{
					"method": "currency",
					"amount": 0,
					"display": "Free",
					"tax": "plus tax",
					"user": "silver"
				}
			]
		},
		{
			"id": "66acd000-77fe-1000-9115-d802584111e8",
			"title": "State of Decay",
			"description": "The end is here. Life as you knew it has gone to hell after the mother of all zombie outbreaks. Now you and the few scattered survivors must band together to survive and rebuild in a 3rd-person action game set in a dynamic open world. You choose where to make your stand, designing and fortifying your home base, performing daring raids for food and ammunition, and rescuing other playable survivors with unique talents.",
			"userRating": {
				"allowed": true,
				"current": {
					"Aggregate": 4.5,
					"Count": 77950
				}
			},
			"originalReleaseDate": "/Date(1370422800000)/",
			"contentRating": {
				"label": "M (Mature)",
				"image": "http://epix.xbox.com/consoleassets/vm_ems/DetailsPages/RatingSystemID/0/default/Values/40.png",
				"age": 17,
				"purchaseAgeGate": true,
				"videoAgeGate": true,
				"descriptors": [
					{
						"label": "Blood and Gore",
						"image": null
					},
					{
						"label": "Drug Reference",
						"image": null
					},
					{
						"label": "Intense Violence",
						"image": null
					},
					{
						"label": "Partial Nudity",
						"image": null
					},
					{
						"label": "Sexual Themes",
						"image": null
					},
					{
						"label": "Strong Language",
						"image": null
					}
				],
				"disclaimers": [
					"Online Interactions Not Rated by the ESRB"
				]
			},
			"childDownloadTypes": [
				"Game",
				"GameDemo",
				"GameVideo",
				"GameAddon"
			],
			"genres": [
				{
					"label": "Action & Adventure"
				},
				{
					"label": "Strategy & Simulation"
				}
			],
			"image": "http://download.xbox.com/content/images/66acd000-77fe-1000-9115-d802584111e8/1033/boxartlg.jpg",
			"url": "/en-US/X8/Game/66acd000-77fe-1000-9115-d802584111e8",
			"downloadTypeClass": "Game",
			"downloadTypeText": "Game",
			"platform": "Xbox",
			"price": {
				"goldPrice": "$19.99",
				"silverPrice": "$19.99"
			},
			"prices": [
				{
					"method": "currency",
					"amount": 19.99,
					"display": "$19.99",
					"tax": "plus tax",
					"user": "silver"
				}
			]
		},
		{
			"id": "7d5cc8fe-3bbc-4bc7-8730-43ae77d4a8d9",
			"title": "Trial Game - State of Decay",
			"description": "The end is here. Life as you knew it has gone to hell after the mother of all zombie outbreaks. Now you and the few scattered survivors must band together to survive and rebuild in a 3rd-person action game set in a dynamic open world. You choose where to make your stand, designing and fortifying your home base, performing daring raids for food and ammunition, and rescuing other playable survivors with unique talents.",
			"userRating": {
				"allowed": false,
				"current": {
					"Aggregate": 0,
					"Count": 0
				}
			},
			"originalReleaseDate": "/Date(1370422800000)/",
			"contentRating": {
				"label": "M (Mature)",
				"image": "http://epix.xbox.com/consoleassets/vm_ems/DetailsPages/RatingSystemID/0/default/Values/40.png",
				"age": 17,
				"purchaseAgeGate": true,
				"videoAgeGate": true,
				"descriptors": [
					{
						"label": "Blood and Gore",
						"image": null
					},
					{
						"label": "Drug Reference",
						"image": null
					},
					{
						"label": "Intense Violence",
						"image": null
					},
					{
						"label": "Partial Nudity",
						"image": null
					},
					{
						"label": "Sexual Themes",
						"image": null
					},
					{
						"label": "Strong Language",
						"image": null
					}
				],
				"disclaimers": [
					"Online Interactions Not Rated by the ESRB"
				]
			},
			"childDownloadTypes": null,
			"genres": [
				{
					"label": "Action & Adventure"
				},
				{
					"label": "Strategy & Simulation"
				}
			],
			"image": "http://download.xbox.com/content/images/7d5cc8fe-3bbc-4bc7-8730-43ae77d4a8d9/1033/boxartlg.jpg",
			"url": "/en-US/X8/Game/7d5cc8fe-3bbc-4bc7-8730-43ae77d4a8d9",
			"downloadTypeClass": "GameDemo",
			"downloadTypeText": "Demo",
			"platform": "Xbox",
			"price": {
				"goldPrice": "Free",
				"silverPrice": "Free"
			},
			"prices": [
				{
					"method": "currency",
					"amount": 0,
					"display": "Free",
					"tax": "plus tax",
					"user": "silver"
				}
			]
		},
		{
			"id": "98687aac-c9cf-47c1-b45f-f0603b0bead9",
			"title": "State of Decay: Breakdown",
			"description": "You've survived State of Decay. Now it's time to move forward and tell your own story.   Take on an endless campaign with twists and turns based entirely on your own choices. Build up your score in the face of an ever-escalating zombie threat, and compete with survivors around the world. Complete challenges to unlock new heroes with unique weapons and skills.  The deeper you go, the tougher it gets, and every choice is yours.",
			"userRating": {
				"allowed": true,
				"current": {
					"Aggregate": 4.5,
					"Count": 2352
				}
			},
			"originalReleaseDate": "/Date(1385715600000)/",
			"contentRating": {
				"label": "M (Mature)",
				"image": "http://epix.xbox.com/consoleassets/vm_ems/DetailsPages/RatingSystemID/0/default/Values/40.png",
				"age": 17,
				"purchaseAgeGate": true,
				"videoAgeGate": true,
				"descriptors": [
					{
						"label": "Blood and Gore",
						"image": null
					},
					{
						"label": "Drug Reference",
						"image": null
					},
					{
						"label": "Intense Violence",
						"image": null
					},
					{
						"label": "Partial Nudity",
						"image": null
					},
					{
						"label": "Sexual Themes",
						"image": null
					},
					{
						"label": "Strong Language",
						"image": null
					}
				],
				"disclaimers": [

				]
			},
			"childDownloadTypes": null,
			"genres": [
				{
					"label": "Action & Adventure"
				},
				{
					"label": "Strategy & Simulation"
				}
			],
			"image": "http://download.xbox.com/content/images/98687aac-c9cf-47c1-b45f-f0603b0bead9/1033/boxartlg.jpg",
			"url": "/en-US/X8/Game/98687aac-c9cf-47c1-b45f-f0603b0bead9",
			"downloadTypeClass": "GameAddon",
			"downloadTypeText": "Add-on",
			"platform": "Xbox",
			"price": {
				"goldPrice": "$6.99",
				"silverPrice": "$6.99"
			},
			"prices": [
				{
					"method": "currency",
					"amount": 6.99,
					"display": "$6.99",
					"tax": "plus tax",
					"user": "silver"
				}
			]
		},
		{
			"id": "f1a9679d-fe4b-4327-84ab-40869a0c25d9",
			"title": "State of Decay: Lifeline",
			"description": "State of Decay: Lifeline puts you into the boots of Greyhound One, a military unit sent into a zombie-infested city to rescue the team of scientists who can put an end to the outbreak.  Lifeline features a new map, new characters, and a new way to play: Defend your base against hordes of zombies, using the best military equipment and personnel your unit can scrape together.  The fate of the city is in your hands. How many people can you save?",
			"userRating": {
				"allowed": true,
				"current": {
					"Aggregate": 4.25,
					"Count": 797
				}
			},
			"originalReleaseDate": "/Date(1401440400000)/",
			"contentRating": {
				"label": "M (Mature)",
				"image": "http://epix.xbox.com/consoleassets/vm_ems/DetailsPages/RatingSystemID/0/default/Values/40.png",
				"age": 17,
				"purchaseAgeGate": true,
				"videoAgeGate": true,
				"descriptors": [
					{
						"label": "Blood and Gore",
						"image": null
					},
					{
						"label": "Drug Reference",
						"image": null
					},
					{
						"label": "Intense Violence",
						"image": null
					},
					{
						"label": "Partial Nudity",
						"image": null
					},
					{
						"label": "Sexual Themes",
						"image": null
					},
					{
						"label": "Strong Language",
						"image": null
					}
				],
				"disclaimers": [

				]
			},
			"childDownloadTypes": null,
			"genres": [
				{
					"label": "Action & Adventure"
				},
				{
					"label": "Strategy & Simulation"
				}
			],
			"image": "http://download.xbox.com/content/images/f1a9679d-fe4b-4327-84ab-40869a0c25d9/1033/boxartlg.jpg",
			"url": "/en-US/X8/Game/f1a9679d-fe4b-4327-84ab-40869a0c25d9",
			"downloadTypeClass": "GameAddon",
			"downloadTypeText": "Add-on",
			"platform": "Xbox",
			"price": {
				"goldPrice": "$6.99",
				"silverPrice": "$6.99"
			},
			"prices": [
				{
					"method": "currency",
					"amount": 6.99,
					"display": "$6.99",
					"tax": "plus tax",
					"user": "silver"
				}
			]
		},
		{
			"id": "36315ee8-4ffb-40c2-9acf-db8eb2404bd0",
			"title": "State of Decay Trailer",
			"description": "The end is here. Life as you knew it has gone to hell after the mother of all zombie outbreaks. Now you and the few scattered survivors must band together to survive and rebuild in a 3rd-person action game set in a dynamic open world. You choose where to make your stand, designing and fortifying your home base, performing daring raids for food and ammunition, and rescuing other playable survivors with unique talents.",
			"userRating": {
				"allowed": true,
				"current": {
					"Aggregate": 4.5,
					"Count": 2397
				}
			},
			"originalReleaseDate": "/Date(1347267600000)/",
			"contentRating": {
				"label": "M (Mature)",
				"image": "http://epix.xbox.com/consoleassets/vm_ems/DetailsPages/RatingSystemID/0/default/Values/40.png",
				"age": 17,
				"purchaseAgeGate": true,
				"videoAgeGate": true,
				"descriptors": [
					{
						"label": "Blood and Gore",
						"image": null
					},
					{
						"label": "Drug Reference",
						"image": null
					},
					{
						"label": "Intense Violence",
						"image": null
					},
					{
						"label": "Partial Nudity",
						"image": null
					},
					{
						"label": "Sexual Themes",
						"image": null
					},
					{
						"label": "Strong Language",
						"image": null
					}
				],
				"disclaimers": [

				]
			},
			"childDownloadTypes": null,
			"genres": [
				{
					"label": "Action & Adventure"
				},
				{
					"label": "Strategy & Simulation"
				}
			],
			"image": "http://download.xbox.com/content/images/66acd000-77fe-1000-9115-d802584111e8/1033/boxartlg.jpg",
			"url": "/en-US/X8/Game/36315ee8-4ffb-40c2-9acf-db8eb2404bd0",
			"downloadTypeClass": "GameVideo",
			"downloadTypeText": "Video",
			"platform": "Xbox",
			"price": {
				"goldPrice": "Free",
				"silverPrice": "Free"
			},
			"prices": [
				{
					"method": "currency",
					"amount": 0,
					"display": "Free",
					"tax": "plus tax",
					"user": "silver"
				}
			]
		}
	]
}
